<?xml version="1.0" encoding="UTF-8" standalone="no"?>

<!--

 user-settings.xml

 Copyright (c) 2011-2013, Daniel Ellermann

 This program is free software: you can redistribute it and/or modify
 it under the terms of the GNU General Public License as published by
 the Free Software Foundation, either version 3 of the License, or
 (at your option) any later version.

 This program is distributed in the hope that it will be useful,
 but WITHOUT ANY WARRANTY; without even the implied warranty of
 MERCHANTABILITY or FITNESS FOR A PARTICULAR PURPOSE.  See the
 GNU General Public License for more details.

 You should have received a copy of the GNU General Public License
 along with this program.  If not, see <http://www.gnu.org/licenses/>.

-->


<databaseChangeLog xmlns="http://www.liquibase.org/xml/ns/dbchangelog"
  xmlns:xsi="http://www.w3.org/2001/XMLSchema-instance"
  xsi:schemaLocation="http://www.liquibase.org/xml/ns/dbchangelog http://www.liquibase.org/xml/ns/dbchangelog/dbchangelog-2.0.xsd">
  <changeSet author="d.ellermann@amc-world.de" id="20121108-1">
    <createTable tableName="user_setting">
      <column autoIncrement="true" name="id" type="bigint">
        <constraints nullable="false" primaryKey="true"
          primaryKeyName="user_settingPK" />
      </column>
      <column name="version" type="bigint">
        <constraints nullable="false" />
      </column>
      <column name="name" type="varchar(255)">
        <constraints nullable="false" />
      </column>
      <column name="user_id" type="bigint">
        <constraints nullable="false" />
      </column>
      <column name="value" type="varchar(255)" />
    </createTable>
    <addForeignKeyConstraint baseTableName="user_setting"
      baseColumnNames="user_id" constraintName="FKD14EA5DC8D1F27AF"
      deferrable="false" initiallyDeferred="false" referencedColumnNames="id"
      referencedTableName="user_data" referencesUniqueColumn="false" />
    <createIndex indexName="FKD14EA5DC8D1F27AF" tableName="user_setting">
      <column name="user_id" />
    </createIndex>
    <createIndex indexName="user_setting_name" tableName="user_setting">
      <column name="user_id" />
      <column name="name" />
    </createIndex>
    <sql>
      INSERT INTO user_setting (version, user_id, name, value)
        SELECT 0 AS version, settings AS user_id, settings_idx AS name,
            settings_elt AS value
          FROM user_data_settings;
    </sql>
  </changeSet>

  <changeSet author="d.ellermann@amc-world.de" id="20121108-2">
    <dropIndex tableName="user_data_settings"
      indexName="user_data_settings_settings_idx" />
    <dropTable tableName="user_data_settings" />
  </changeSet>
</databaseChangeLog>
